README.md
as7343.py
as7343_micropython-1.0.0.dist-info/METADATA
as7343_micropython-1.0.0.dist-info/WHEEL
as7343_micropython-1.0.0.dist-info/licenses/LICENSE.txt
as7343_micropython-1.0.0.dist-info/RECORD
