Metadata-Version: 2.3
Name: as7343-micropython
Version: 1.0.0
Summary:  MicroPython device library for the AS7343 14-channel spectral sensor
Project-URL: GitHub, https://www.github.com/pimoroni/as7343-micropython
Project-URL: Homepage, https://www.pimoroni.com
Author-email: Phil <phil@pimoroni.com>
License-File: LICENSE.txt
Classifier: License :: OSI Approved :: MIT License
